{"lastName": "Hopkins", "objectUrn": "urn:li:member:51740724", "contactInfo": {}, "crmStatus": {"imported": false}, "industry": "Law Enforcement", "educations": [{"endedOn": {"year": 1979}, "fieldsOfStudy": ["Accounting"], "school": "urn:li:fs_salesSchool:18350", "degree": "BS", "schoolName": "Indiana University\u00e2\u0080\u0093Purdue University Indianapolis", "startedOn": {"year": 1975}, "eduId": 38754221}], "inmailRestriction": "NO_RESTRICTION", "unlocked": false, "entityUrn": "urn:li:fs_salesProfile:(ACwAAAMVgDQBGhmTb3P3pfRU0DoJi9l1gGUDO94,NAME_SEARCH,undefined)", "numOfConnections": 2, "showTotalConnectionsPage": false, "headline": "Unit Chief at U.S. Immigration and Customs Enforcement (ICE)", "profileUnlockInfo": {"showProfileUnlock": false}, "pendingInvitation": false, "defaultPosition": {"posId": 91325880, "new": false, "current": true, "companyName": "U.S. Immigration and Customs Enforcement (ICE)", "description": "I am responsible for oversight of budget execution, budget formulation, human capitol, procurement, advanced acquisition planning, travel, permanent change of station (PCS), logistics, fleet management, purchase card, facilities and property.", "title": "Unit Chief", "startedOn": {"month": 9, "year": 2006}, "companyUrn": "urn:li:fs_salesCompany:533534"}, "degree": 3, "fullName": "Wilson Hopkins", "positions": [{"posId": 91325880, "new": false, "current": true, "companyName": "U.S. Immigration and Customs Enforcement (ICE)", "description": "I am responsible for oversight of budget execution, budget formulation, human capitol, procurement, advanced acquisition planning, travel, permanent change of station (PCS), logistics, fleet management, purchase card, facilities and property.", "title": "Unit Chief", "startedOn": {"month": 9, "year": 2006}, "companyUrn": "urn:li:fs_salesCompany:533534"}], "pictureInfo": {}, "relatedColleagueCompanyId": 533534, "savedLead": false, "firstName": "Wilson", "numOfSharedConnections": 0, "memberBadges": {"premium": false, "openLink": false, "jobSeeker": false}, "flagshipProfileUrl": "https://www.linkedin.com/in/wilson-hopkins-6703b215", "location": "Washington D.C. Metro Area"}