{"lastName": "B.", "objectUrn": "urn:li:member:598158588", "contactInfo": {}, "crmStatus": {"imported": false}, "industry": "Computer & Network Security", "educations": [{"endedOn": {"year": 2017}, "fieldsOfStudy": ["Computer Science and Engineering"], "school": "urn:li:fs_salesSchool:19028", "degree": "Master of Science - MS", "schoolName": "University at Buffalo", "startedOn": {"year": 2015}, "eduId": 442560030}, {"endedOn": {"year": 2015}, "fieldsOfStudy": ["Computer Engineering"], "school": "urn:li:fs_salesSchool:13666", "degree": "Bachelor of Engineering - BE", "schoolName": "University of Pune", "startedOn": {"year": 2011}, "eduId": 442559203}], "inmailRestriction": "NO_RESTRICTION", "unlocked": false, "entityUrn": "urn:li:fs_salesProfile:(ACwAACOnLPwBsmx1aa608J0SZdY-pyLOaQZq8XU,NAME_SEARCH,undefined)", "numOfConnections": 91, "showTotalConnectionsPage": false, "headline": "Cyber Security Engineer at U.S. Immigration and Customs Enforcement (ICE) | CyberCorps, SFS", "profileUnlockInfo": {"showProfileUnlock": false}, "summary": "Incident Responder.\n\nEducation:\n1. Master of Science (M.S.) in Computer Science & Engineering - (3.94/4.0) - May 2017\n2. Bachelor of Science (B.S.) in Computer Engineering - (3.55/4.0) - May 2015\n\nCertificates:\n1. Advanced Certificate in Information Assurance, NSA|DHS - May 2017\n2. Tanium: Foundation, Operations, Incident Response and Hunting - Jan 2018\n3. Intelligence Driven Defense using the Lockheed Martin Cyber Kill Chain - Feb 2018\n4. Splunk Certified User - March 2018\n5. CISSP - Est. June 2018", "pendingInvitation": false, "defaultPosition": {"posId": 1052917803, "new": false, "current": true, "companyName": "U.S. Immigration and Customs Enforcement (ICE)", "description": "CyberCorps, SFS Fulfillment", "title": "Cyber Security Engineer | Incident Response & Cyber Threat Intelligence ", "startedOn": {"month": 5, "year": 2017}, "companyUrn": "urn:li:fs_salesCompany:533534"}, "degree": 3, "fullName": "Tanmay B.", "positions": [{"posId": 1052917803, "new": false, "current": true, "companyName": "U.S. Immigration and Customs Enforcement (ICE)", "description": "CyberCorps, SFS Fulfillment", "title": "Cyber Security Engineer | Incident Response & Cyber Threat Intelligence ", "startedOn": {"month": 5, "year": 2017}, "companyUrn": "urn:li:fs_salesCompany:533534"}, {"posId": 1052918718, "new": false, "current": false, "endedOn": {"month": 5, "year": 2017}, "companyName": "University at Buffalo", "title": "Sr. Cyber Security Researcher", "startedOn": {"month": 8, "year": 2016}, "companyUrn": "urn:li:fs_salesCompany:6502"}, {"posId": 1052919190, "new": false, "current": false, "endedOn": {"month": 8, "year": 2016}, "companyName": "U.S. Department of Homeland Security", "description": "CyberCorps, SFS Fulfillment: Internship", "title": "Cyber Hunt & Incident Response Analyst | US-CERT", "startedOn": {"month": 5, "year": 2016}, "companyUrn": "urn:li:fs_salesCompany:2998"}, {"posId": 1052919616, "new": false, "current": false, "endedOn": {"month": 5, "year": 2016}, "companyName": "University at Buffalo", "title": "Cyber Security Researcher", "startedOn": {"month": 5, "year": 2015}, "companyUrn": "urn:li:fs_salesCompany:6502"}], "pictureInfo": {}, "relatedColleagueCompanyId": 533534, "savedLead": false, "firstName": "Tanmay", "numOfSharedConnections": 0, "memberBadges": {"premium": false, "openLink": false, "jobSeeker": false}, "flagshipProfileUrl": "https://www.linkedin.com/in/usmarine93", "location": "Washington D.C. Metro Area"}