{"pendingInvitation": false, "defaultPosition": {"posId": 763866894, "new": false, "current": true, "companyName": "US Immigration and Customs Enforcement", "location": "Washington D.C. Metro Area", "title": "Unit Chief, National Passport Program Manager", "startedOn": {"month": 2, "year": 2007}}, "objectUrn": "urn:li:member:350482096", "contactInfo": {}, "crmStatus": {"imported": false}, "degree": -1, "fullName": "", "industry": "-1", "positions": [{"posId": 763866894, "new": false, "current": true, "companyName": "US Immigration and Customs Enforcement", "location": "Washington D.C. Metro Area", "title": "Unit Chief, National Passport Program Manager", "startedOn": {"month": 2, "year": 2007}}], "educations": [{"fieldsOfStudy": ["Business Administration and Management, General"], "school": "urn:li:fs_salesSchool:18706", "degree": "bachelor of Science, Management", "schoolName": "Park University", "eduId": 326225080}], "pictureInfo": {}, "inmailRestriction": "NO_RESTRICTION", "savedLead": false, "unlocked": false, "numOfSharedConnections": 0, "memberBadges": {"premium": false, "openLink": false, "jobSeeker": false}, "entityUrn": "urn:li:fs_salesProfile:(ACwAABTj7rABfGlb4zscLxPE5pg1o796jiWQoaE,NAME_SEARCH,undefined)", "numOfConnections": 14, "flagshipProfileUrl": "https://www.linkedin.com/in/lewis-baker-35446199", "location": "United States", "showTotalConnectionsPage": false, "headline": "--", "profileUnlockInfo": {"showProfileUnlock": false}}